{
    "amazon": {
        "email": "sahilchanglani@gmail.com",
        "password": "N8()uxzsZMj$9E"
    },
    "facebook": {
        "email": "sahilchanglani@gmail.com",
        "password": "asasjhkcsakand"
    },
    "insta": {
        "email": "sahilchanglani@gmail.com",
        "password": "sajbdsak"
    },
    "meetgajra.com": {
        "email": "sahilchanglani@gmail.com",
        "password": "hdkasnkj"
    },
    "sasifookin.com": {
        "email": "sahilchanglani@gmail.com",
        "password": "M6Fy8%o%ZYkxeb"
    }
}